LICENSE
MANIFEST.in
README.rst
setup.py
cmsplugin_syntax_highlight/__init__.py
cmsplugin_syntax_highlight/cms_plugins.py
cmsplugin_syntax_highlight/models.py
cmsplugin_syntax_highlight/utils.py
cmsplugin_syntax_highlight.egg-info/PKG-INFO
cmsplugin_syntax_highlight.egg-info/SOURCES.txt
cmsplugin_syntax_highlight.egg-info/dependency_links.txt
cmsplugin_syntax_highlight.egg-info/not-zip-safe
cmsplugin_syntax_highlight.egg-info/top_level.txt
cmsplugin_syntax_highlight/migrations/0001_initial.py
cmsplugin_syntax_highlight/migrations/__init__.py
cmsplugin_syntax_highlight/static/cmsplugin_syntax_highlight/icon.png
cmsplugin_syntax_highlight/templates/cmsplugin_syntax_highlight/bash.html
cmsplugin_syntax_highlight/templates/cmsplugin_syntax_highlight/cpp.html
cmsplugin_syntax_highlight/templates/cmsplugin_syntax_highlight/csharp.html
cmsplugin_syntax_highlight/templates/cmsplugin_syntax_highlight/css.html
cmsplugin_syntax_highlight/templates/cmsplugin_syntax_highlight/diff.html
cmsplugin_syntax_highlight/templates/cmsplugin_syntax_highlight/java.html
cmsplugin_syntax_highlight/templates/cmsplugin_syntax_highlight/javascript.html
cmsplugin_syntax_highlight/templates/cmsplugin_syntax_highlight/perl.html
cmsplugin_syntax_highlight/templates/cmsplugin_syntax_highlight/php.html
cmsplugin_syntax_highlight/templates/cmsplugin_syntax_highlight/plain.html
cmsplugin_syntax_highlight/templates/cmsplugin_syntax_highlight/python.html
cmsplugin_syntax_highlight/templates/cmsplugin_syntax_highlight/ruby.html
cmsplugin_syntax_highlight/templates/cmsplugin_syntax_highlight/sass.html
cmsplugin_syntax_highlight/templates/cmsplugin_syntax_highlight/scala.html
cmsplugin_syntax_highlight/templates/cmsplugin_syntax_highlight/sql.html
cmsplugin_syntax_highlight/templates/cmsplugin_syntax_highlight/vb.html
cmsplugin_syntax_highlight/templates/cmsplugin_syntax_highlight/xml.html