Metadata-Version: 1.1
Name: cmsplugin-syntax-highlight
Version: 0.1.5
Summary: DjangoCMS syntax highlighting plugin allowing for easy integration with SyntaxHighlighter.
Home-page: http://github.com/nmurrin
Author: Norm Murrin
Author-email: norman.murrin@gmail.com
License: Simplified BSD License
Platform: UNKNOWN
Classifier: Development Status :: 3 - Alpha
Classifier: Environment :: Plugins
Classifier: Intended Audience :: Developers
Classifier: License :: OSI Approved :: BSD License
Classifier: Operating System :: OS Independent
Classifier: Programming Language :: Python
Classifier: Framework :: Django
Provides: cmsplugin_syntax_highlight
